{"mlbPitcherId":"669456","name":"Shane Bieber","season":2026,"gameLog":[{"date":"2026-06-23","outs":11,"gamesStarted":1},{"date":"2026-06-28","outs":16,"gamesStarted":1},{"date":"2026-07-04","outs":12,"gamesStarted":1},{"date":"2026-07-10","outs":14,"gamesStarted":1}],"yearByYear":[{"season":2018,"outs":344},{"season":2019,"outs":643},{"season":2020,"outs":232},{"season":2021,"outs":290},{"season":2022,"outs":600},{"season":2023,"outs":384},{"season":2024,"outs":36},{"season":2025,"outs":121},{"season":2026,"outs":53}]}